{
  "linux_basic_commands": true,
  "linux_file_operations": true,
  "linux_permissions": true,
  "linux_text_processing": true,
  "linux_process_mgmt": true,
  "linux_system_info": true,
  "linux_package_mgmt": true,
  "linux_user_mgmt": false,
  "linux_cron_jobs": false,
  "linux_log_analysis": false,
  "scripting_bash_basics": false,
  "scripting_bash_advanced": false,
  "scripting_python_basics": false,
  "scripting_python_modules": false,
  "scripting_automation_scripts": false,
  "scripting_error_handling": false,
  "scripting_script_deployment": false,
  "scripting_config_management": false,
  "docker_docker_concepts": true,
  "docker_dockerfile": true,
  "docker_docker_commands": true,
  "docker_volumes_networks": true,
  "docker_docker_compose": false,
  "docker_registry_mgmt": false,
  "docker_security": false,
  "docker_optimization": false,
  "yaml_json_yaml_syntax": false,
  "yaml_json_json_syntax": false,
  "yaml_json_data_validation": false,
  "yaml_json_templating": false,
  "yaml_json_config_files": false,
  "yaml_json_api_responses": false,
  "networking_osi_model": false,
  "networking_ip_subnetting": false,
  "networking_dns_concepts": false,
  "networking_load_balancing": false,
  "networking_firewalls": false,
  "networking_network_tools": false,
  "networking_ssl_tls": false,
  "networking_vpn_concepts": false,
  "sdlc_sdlc_phases": false,
  "sdlc_agile_scrum": false,
  "sdlc_waterfall": false,
  "sdlc_devops_integration": false,
  "sdlc_quality_assurance": false,
  "sdlc_deployment_strategies": false,
  "git_git_basics": false,
  "git_branching": false,
  "git_git_workflow": false,
  "git_conflict_resolution": false,
  "git_git_hooks": false,
  "git_github_features": false,
  "git_code_review": false,
  "git_git_advanced": false,
  "jenkins_jenkins_setup": false,
  "jenkins_pipeline_syntax": false,
  "jenkins_build_jobs": false,
  "jenkins_pipeline_stages": false,
  "jenkins_jenkins_plugins": false,
  "jenkins_build_triggers": false,
  "jenkins_artifacts": false,
  "jenkins_jenkins_security": false,
  "github_actions_workflow_syntax": false,
  "github_actions_actions_marketplace": false,
  "github_actions_ci_workflows": false,
  "github_actions_cd_workflows": false,
  "github_actions_secrets_management": false,
  "github_actions_matrix_builds": false,
  "github_actions_custom_actions": false,
  "github_actions_workflow_optimization": false,
  "testing_unit_testing": false,
  "testing_integration_testing": false,
  "testing_e2e_testing": false,
  "testing_test_automation": false,
  "testing_code_coverage": false,
  "testing_performance_testing": false,
  "testing_security_testing": false,
  "testing_test_reporting": false,
  "deployment_deployment_strategies": false,
  "deployment_rollback_mechanisms": false,
  "deployment_env_management": false,
  "deployment_config_management": false,
  "deployment_release_automation": false,
  "deployment_deployment_tools": false,
  "deployment_database_migrations": false,
  "deployment_monitoring_deployment": false,
  "aws_aws_basics": false,
  "aws_ec2": false,
  "aws_s3": false,
  "aws_iam": false,
  "aws_vpc": false,
  "aws_rds": false,
  "aws_cloudwatch": false,
  "aws_lambda": false,
  "aws_elb": false,
  "aws_aws_cli": false,
  "terraform_terraform_basics": false,
  "terraform_terraform_state": false,
  "terraform_terraform_modules": false,
  "terraform_terraform_variables": false,
  "terraform_terraform_provisioners": false,
  "terraform_terraform_workspaces": false,
  "terraform_terraform_import": false,
  "terraform_terraform_best_practices": false,
  "k8s_k8s_architecture": false,
  "k8s_pods": false,
  "k8s_deployments": false,
  "k8s_services": false,
  "k8s_configmaps_secrets": false,
  "k8s_ingress": false,
  "k8s_volumes": false,
  "k8s_rbac": false,
  "k8s_kubectl": false,
  "k8s_troubleshooting": false,
  "helm_helm_basics": false,
  "helm_helm_templates": false,
  "helm_helm_hooks": false,
  "helm_kustomize_basics": false,
  "helm_kustomize_patches": false,
  "helm_package_management": false,
  "helm_helm_security": false,
  "prometheus_prometheus_basics": false,
  "prometheus_metrics_collection": false,
  "prometheus_promql": false,
  "prometheus_alerting_rules": false,
  "prometheus_grafana_dashboards": false,
  "prometheus_grafana_alerts": false,
  "prometheus_service_discovery": false,
  "prometheus_monitoring_best_practices": false,
  "elk_elasticsearch": false,
  "elk_logstash": false,
  "elk_kibana": false,
  "elk_filebeat": false,
  "elk_fluentd": false,
  "elk_log_parsing": false,
  "elk_index_management": false,
  "elk_security_logging": false,
  "cloudwatch_cloudwatch_metrics": false,
  "cloudwatch_cloudwatch_logs": false,
  "cloudwatch_cloudwatch_alarms": false,
  "cloudwatch_cloudwatch_dashboards": false,
  "cloudwatch_datadog_basics": false,
  "cloudwatch_datadog_dashboards": false,
  "cloudwatch_datadog_alerts": false,
  "cloudwatch_apm_tracing": false,
  "incident_incident_response": false,
  "incident_on_call_practices": false,
  "incident_escalation_procedures": false,
  "incident_incident_tools": false,
  "incident_post_incident": false,
  "incident_runbooks": false,
  "incident_communication": false,
  "incident_metrics_tracking": false,
  "slo_sli_definition": false,
  "slo_slo_setting": false,
  "slo_sla_management": false,
  "slo_error_budget": false,
  "slo_slo_monitoring": false,
  "slo_slo_reporting": false,
  "budget_error_budget_concept": false,
  "budget_toil_identification": false,
  "budget_automation_prioritization": false,
  "budget_capacity_planning": false,
  "budget_reliability_engineering": false,
  "budget_toil_reduction": false,
  "rca_incident_classification": false,
  "rca_incident_response_process": false,
  "rca_rca_methodology": false,
  "rca_blameless_postmortem": false,
  "rca_action_items": false,
  "rca_incident_prevention": false,
  "rca_communication_protocols": false,
  "rca_learning_culture": false,
  "automation_infrastructure_automation": false,
  "automation_deployment_automation": false,
  "automation_testing_automation": false,
  "automation_monitoring_automation": false,
  "automation_self_healing": false,
  "automation_auto_scaling": false,
  "automation_pipeline_optimization": false,
  "automation_automation_testing": false,
  "chaos_chaos_principles": false,
  "chaos_chaos_tools": false,
  "chaos_failure_injection": false,
  "chaos_blast_radius": false,
  "chaos_chaos_experiments": false,
  "chaos_resilience_testing": false,
  "chaos_gamedays": false,
  "chaos_chaos_automation": false,
  "notes": {
    "to_learn": "",
    "in_progress": "",
    "completed": ""
  }
}